odoo/addons/pos_membership/README.rst
odoo/addons/pos_membership/__init__.py
odoo/addons/pos_membership/__manifest__.py
odoo/addons/pos_membership/demo/res_partner.xml
odoo/addons/pos_membership/i18n/es.po
odoo/addons/pos_membership/i18n/fr.po
odoo/addons/pos_membership/i18n/it.po
odoo/addons/pos_membership/i18n/pos_membership.pot
odoo/addons/pos_membership/models/__init__.py
odoo/addons/pos_membership/models/pos_session.py
odoo/addons/pos_membership/models/res_partner.py
odoo/addons/pos_membership/readme/CONTRIBUTORS.rst
odoo/addons/pos_membership/readme/CREDITS.rst
odoo/addons/pos_membership/readme/DESCRIPTION.rst
odoo/addons/pos_membership/static/description/icon.png
odoo/addons/pos_membership/static/description/index.html
odoo/addons/pos_membership/static/description/pos_ui_partner_form.png
odoo/addons/pos_membership/static/description/pos_ui_partner_tree.png
odoo/addons/pos_membership/static/description/pos_warning_sell_membership_product.png
odoo/addons/pos_membership/static/src/css/pos_membership.css
odoo/addons/pos_membership/static/src/js/PaymentScreen.js
odoo/addons/pos_membership/static/src/xml/PartnerDetailsEdit.xml
odoo/addons/pos_membership/static/src/xml/PartnerLine.xml
odoo_addon_pos_membership-16.0.1.0.1.dist-info/METADATA
odoo_addon_pos_membership-16.0.1.0.1.dist-info/WHEEL
odoo_addon_pos_membership-16.0.1.0.1.dist-info/top_level.txt
odoo_addon_pos_membership-16.0.1.0.1.dist-info/RECORD
